xlsxtools.py
xlsxtools-0.2.0.dist-info/LICENSE
xlsxtools-0.2.0.dist-info/WHEEL
xlsxtools-0.2.0.dist-info/METADATA
xlsxtools-0.2.0.dist-info/RECORD
