Metadata-Version: 2.3
Name: xlsxtools
Version: 0.2.0
Summary: xlsxtools: Utility functions for writing and manipulating Excel files
Author-email: Josh Burnett <github@burnettsonline.org>
Requires-Python: >=3.8
Classifier: License :: OSI Approved :: MIT License
Requires-Dist: pandas
Requires-Dist: openpyxl
Project-URL: Home, https://github.com/joshburnett/xlsxtools
